{
  "id": "d72c3f64-913c-4ef4-bba1-c821aee18e38",
  "correlationId": "5274ede1-142a-4577-a4f5-4b5125de8c84",
  "rawIntent": "Read the current package.json and fix the tsx version from ^0.0.0 to ^4.7.0",
  "scope": {
    "affectedDomains": [
      "package.json"
    ],
    "affectedLayers": [
      "config"
    ],
    "isBreakingChange": false,
    "estimatedComplexity": "small"
  },
  "successCriteria": [
    {
      "id": "sc-001",
      "description": "The tsx version in package.json is updated to ^4.7.0",
      "testable": true,
      "layer": "unit"
    }
  ],
  "constraints": [
    "Input validated at the API boundary",
    "No sensitive data in logs"
  ],
  "outOfScope": [
    "everything outside package.json"
  ],
  "ambiguities": []
}